bert_sent_encoding/__init__.py
bert_sent_encoding/main.py
bert_sent_encoding/pytorch_pretrained_bert/__init__.py
bert_sent_encoding/pytorch_pretrained_bert/__main__.py
bert_sent_encoding/pytorch_pretrained_bert/file_utils.py
bert_sent_encoding/pytorch_pretrained_bert/modeling.py
bert_sent_encoding/pytorch_pretrained_bert/optimization.py
bert_sent_encoding/pytorch_pretrained_bert/tokenization.py
bert_sent_encoding/pytorch_pretrained_bert/__pycache__/__init__.cpython-36.pyc
bert_sent_encoding/pytorch_pretrained_bert/__pycache__/__init__.cpython-37.pyc
bert_sent_encoding/pytorch_pretrained_bert/__pycache__/file_utils.cpython-36.pyc
bert_sent_encoding/pytorch_pretrained_bert/__pycache__/file_utils.cpython-37.pyc
bert_sent_encoding/pytorch_pretrained_bert/__pycache__/modeling.cpython-36.pyc
bert_sent_encoding/pytorch_pretrained_bert/__pycache__/modeling.cpython-37.pyc
bert_sent_encoding/pytorch_pretrained_bert/__pycache__/optimization.cpython-36.pyc
bert_sent_encoding/pytorch_pretrained_bert/__pycache__/optimization.cpython-37.pyc
bert_sent_encoding/pytorch_pretrained_bert/__pycache__/tokenization.cpython-36.pyc
bert_sent_encoding/pytorch_pretrained_bert/__pycache__/tokenization.cpython-37.pyc
bert_sent_encoding-0.2.0.dist-info/METADATA
bert_sent_encoding-0.2.0.dist-info/WHEEL
bert_sent_encoding-0.2.0.dist-info/top_level.txt
bert_sent_encoding-0.2.0.dist-info/RECORD
