Metadata-Version: 2.1
Name: bert-sent-encoding
Version: 0.2.0
Summary: A bert sentence encoding tool
Home-page: https://gitlab.leihuo.netease.com/shaojianzhi/bert-sent-encoding
Author: Shao Jianzhi
Author-email: shaojianzhi2012@163.com
License: BSD
Platform: UNKNOWN
Requires-Dist: tqdm
Requires-Dist: boto3
Requires-Dist: botocore
Requires-Dist: requests
Requires-Dist: numpy
Requires-Dist: torch
